Metadata-Version: 1.0
Name: gen-names-wmilczarek
Version: 2.0.0
Summary: Generate random names with length
Home-page: https://github.com/treyhunner/names
Author: Wojciech Milczarek
Author-email: wojciechjakubmilczarek@gmail.com
License: UNKNOWN
Keywords: random names
Platform: UNKNOWN
